{
  "generated_at": "2025-07-10T15:34:54.918124013+07:00",
  "total": 11,
  "groups": {
    "Animation": [
      {
        "name": "Cars.ico",
        "path": "/mnt/c/Users/Rizki/OneDrive/Pictures/Icons/Downloaded Icon Pack/Movie Icon Pack/downloaded/Animation/Cars.ico",
        "source": "downloaded"
      }
    ],
    "Comedy": [
      {
        "name": "Vacation (2015).ico",
        "path": "/mnt/c/Users/Rizki/OneDrive/Pictures/Icons/Downloaded Icon Pack/Movie Icon Pack/downloaded/Comedy/Vacation (2015).ico",
        "source": "downloaded"
      }
    ],
    "Horror": [
      {
        "name": "The Thing (1982).ico",
        "path": "/mnt/c/Users/Rizki/OneDrive/Pictures/Icons/Downloaded Icon Pack/Movie Icon Pack/downloaded/Horror/The Thing (1982).ico",
        "source": "downloaded"
      }
    ],
    "Sci-Fi": [
      {
        "name": "[COLLECTION] Alien Anthology (1979-2024)",
        "path": ""
      },
      {
        "name": "[COLLECTION] DC Extended Universe (2013-2023)",
        "path": ""
      },
      {
        "name": "[COLLECTION] Marvel Cinematic Universe (2008-2025)",
        "path": ""
      },
      {
        "name": "[COLLECTION] Planet of the Apes - Reboot Timeline (2011-2024)",
        "path": ""
      },
      {
        "name": "[COLLECTION] Predator (1987-2022)",
        "path": ""
      },
      {
        "name": "[COLLECTION] The Hunger Games (2012-2023)",
        "path": ""
      },
      {
        "name": "[COLLECTION] Transformers (2007-2023)",
        "path": ""
      },
      {
        "name": "[COLLECTION] X-Men Saga (2000-2020)",
        "path": ""
      }
    ]
  }
}
